dgapplock/__init__.py
dgapplock/base.py
dgapplock/exceptions.py
dgapplock/old_redis_back.py
dgapplock/pg_backend.py
dgapplock/redis_backend.py
dgapplock-2.0.0a2.dist-info/METADATA
dgapplock-2.0.0a2.dist-info/WHEEL
dgapplock-2.0.0a2.dist-info/licenses/LICENSE
dgapplock-2.0.0a2.dist-info/RECORD
