Metadata-Version: 2.4
Name: dgapplock
Version: 2.0.0a2
Summary: AppLocker
License: MIT
License-File: LICENSE
Keywords: sqlalchemy,client,postgresql,mssql,oracle
Author: r.rasputin
Author-email: r.rasputin@s7.ru
Requires-Python: >=3.12
Classifier: Development Status :: 4 - Beta
Classifier: Intended Audience :: Developers
Classifier: License :: OSI Approved :: MIT License
Classifier: Programming Language :: Python :: 3.10
Classifier: Programming Language :: Python :: 3.11
Classifier: Programming Language :: Python :: 3.12
Classifier: Programming Language :: Python :: 3.13
Classifier: Operating System :: OS Independent
Classifier: Topic :: Software Development :: Libraries :: Python Modules
Classifier: Topic :: System :: Distributed Computing
Provides-Extra: pg
Provides-Extra: redis
Requires-Dist: dglog (>=1.0.0.1)
Requires-Dist: dgredis ; extra == "redis"
Requires-Dist: psycopg2-binary ; extra == "pg"
Requires-Dist: pydantic
Requires-Dist: redis ; extra == "redis"
